probe_internet.py
probe_internet-0.1.2.dist-info/entry_points.txt
probe_internet-0.1.2.dist-info/WHEEL
probe_internet-0.1.2.dist-info/METADATA
probe_internet-0.1.2.dist-info/RECORD
